pyeasyedit/LexersCustom.py
pyeasyedit/__init__.py
pyeasyedit/__main__.py
pyeasyedit/pyeasylib.py
pyeasyedit/images/easyedit.png
pyeasyedit/images/icon.png
pyeasyedit/images/wright_bros.png
pyeasyedit-0.1.22.dist-info/LICENSE
pyeasyedit-0.1.22.dist-info/METADATA
pyeasyedit-0.1.22.dist-info/WHEEL
pyeasyedit-0.1.22.dist-info/entry_points.txt
pyeasyedit-0.1.22.dist-info/top_level.txt
pyeasyedit-0.1.22.dist-info/RECORD
