Metadata-Version: 2.1
Name: pyeasyedit
Version: 0.1.22
Summary: A PyQt6 multi-tabbed editor based on QScintilla, includes limited IDE functions via Jedi
Home-page: https://github.com/scottpeterman/pyeasyedit
Author: Scott Peterman
Author-email: scottpeterman@gmail.com
License: GPLv3
Platform: UNKNOWN
Classifier: Programming Language :: Python :: 3.8
Classifier: License :: OSI Approved :: GNU General Public License v3 (GPLv3)
Classifier: Operating System :: OS Independent
License-File: LICENSE
Requires-Dist: PyQt6 >=6.6.1
Requires-Dist: PyQt6-Qt6 >=6.6.2
Requires-Dist: PyQt6-sip >=13.6.0
Requires-Dist: PyQt6-QScintilla >=2.14.1
Requires-Dist: jedi >=0.19.1
